llama_index/callbacks/langfuse/__init__.py
llama_index/callbacks/langfuse/base.py
llama_index_callbacks_langfuse-0.4.1.dist-info/METADATA
llama_index_callbacks_langfuse-0.4.1.dist-info/WHEEL
llama_index_callbacks_langfuse-0.4.1.dist-info/licenses/LICENSE
llama_index_callbacks_langfuse-0.4.1.dist-info/RECORD
