Metadata-Version: 2.4
Name: llama-index-callbacks-langfuse
Version: 0.4.1
Summary: llama-index callbacks langfuse integration
Author-email: Your Name <you@example.com>
License-Expression: MIT
License-File: LICENSE
Requires-Python: <4.0,>=3.9
Requires-Dist: langfuse<3,>=2.21.2
Requires-Dist: llama-index-core<0.15,>=0.13.0
